GradientTransformation/__init__.py
GradientTransformation/lbfgs.py
examples/quadratic.py
examples/rosenbrock.py
GradientTransformation-1.0.0.dist-info/LICENSE
GradientTransformation-1.0.0.dist-info/METADATA
GradientTransformation-1.0.0.dist-info/WHEEL
GradientTransformation-1.0.0.dist-info/top_level.txt
GradientTransformation-1.0.0.dist-info/RECORD
