Metadata-Version: 2.1
Name: GradientTransformation
Version: 1.0.0
Summary: A JAX-based L-BFGS optimizer
Author-email: Joseph Schafer <joeschafer28@gmail.com>
License: MIT
Project-URL: Repository, https://github.com/JWSch4fer/LBFGS_JAX
Keywords: jax,optimizer,lbfgs,optimization
Classifier: Programming Language :: Python :: 3
Classifier: License :: OSI Approved :: MIT License
Classifier: Operating System :: OS Independent
Requires-Python: >=3.10
License-File: LICENSE
Requires-Dist: jax>=0.4.28
Requires-Dist: jaxlib>=0.4.28
